Workbook

Sheet Dashboard_Cliente
B2: Monitor Jurídico | Precificação (Resumo para Aprovação)
B4: Edite os campos em azul (assumptions) e avalie Setup + Mensalidade por faixa de volume. Valores calculados automaticamente.
B6: Premissas (Inputs) | E6: Indicadores (para leitura rápida)
B7: Custo de descoberta por CPF/CNPJ (R$) | C7: 3.05 | E7: Entidades (cenário) | F7: =Pricing!A5 -> 20000 | G7: Setup sugerido | H7: =ROUND(Pricing!B5,2) -> 203333.33 | I7: Mensalidade sugerida
B8: Custo de atualização por processo (R$) | C8: 0.04 | E8: Custo API mensal estimado | F8: =ROUND(Custos!C5,2) -> 2400 | G8: Payback (meses) | H8: =ROUND(Financial_Model!I5,1) -> 0.3 | I8: =ROUND(Pricing!C5,2) -> 8000
B9: Média de processos por entidade | C9: 3
B10: Margem desejada (%) | C10: 0.7
B11: Prazo de contrato (meses) | C11: 24
B12: CAC estimado por cliente (R$) | C12: 2000
B14: Tabela de Precificação por Volume (proposta)
B15: Plano | C15: Entidades | D15: Setup (R$) | E15: Mensal (R$) | F15: Custo API Mensal (R$) | G15: LTV 24m (R$) | H15: Lucro Bruto 24m (R$)
B16: Starter | C16: =Pricing!A2 -> 150 | D16: =ROUND(Pricing!B2,2) -> 1525 | E16: =ROUND(Pricing!C2,2) -> 60 | F16: =ROUND(Custos!C2,2) -> 18 | G16: =ROUND(Financial_Model!F2,2) -> 2965 | H16: =ROUND(Financial_Model!H2,2) -> 2075.5
B17: Business | C17: =Pricing!A3 -> 2000 | D17: =ROUND(Pricing!B3,2) -> 20333.33 | E17: =ROUND(Pricing!C3,2) -> 800 | F17: =ROUND(Custos!C3,2) -> 240 | G17: =ROUND(Financial_Model!F3,2) -> 39533.33 | H17: =ROUND(Financial_Model!H3,2) -> 27673.33
B18: Corporate | C18: =Pricing!A4 -> 5000 | D18: =ROUND(Pricing!B4,2) -> 50833.33 | E18: =ROUND(Pricing!C4,2) -> 2000 | F18: =ROUND(Custos!C4,2) -> 600 | G18: =ROUND(Financial_Model!F4,2) -> 98833.33 | H18: =ROUND(Financial_Model!H4,2) -> 69183.33
B19: Enterprise | C19: =Pricing!A5 -> 20000 | D19: =ROUND(Pricing!B5,2) -> 203333.33 | E19: =ROUND(Pricing!C5,2) -> 8000 | F19: =ROUND(Custos!C5,2) -> 2400 | G19: =ROUND(Financial_Model!F5,2) -> 395333.33 | H19: =ROUND(Financial_Model!H5,2) -> 276733.33
B22: Observações: 1) Setup cobre o custo de descoberta inicial (consulta por CPF/CNPJ) e implantação. 2) Mensalidade cobre monitoramento e atualizações. Custos de API variam conforme volume e profundidade de dados (documentos, autos, etc.). Referência de cobrança: https://api.escavador.com/servicos

Sheet Parametros
A1: Parametro | B1: Valor
A2: Custo Descoberta por CPF/CNPJ (R$) | B2: =Dashboard_Cliente!C7 -> 3.05
A3: Custo Atualizacao por Processo (R$) | B3: =Dashboard_Cliente!C8 -> 0.04
A4: Media de Processos por Entidade | B4: =Dashboard_Cliente!C9 -> 3
A5: Margem Desejada | B5: =Dashboard_Cliente!C10 -> 0.7
A6: Prazo de contrato (meses) | B6: =Dashboard_Cliente!C11 -> 24

Sheet Volumes
A1: Entidades Monitoradas
A2: 150
A3: 2000
A4: 5000
A5: 20000

Sheet Custos
A1: Entidades | B1: Custo Implantacao | C1: Custo Mensal
A2: =Volumes!A2 -> 150 | B2: =A2*Parametros!B2 -> 457.5 | C2: =A2*Parametros!B4*Parametros!B3 -> 18
A3: =Volumes!A3 -> 2000 | B3: =A3*Parametros!B2 -> 6100 | C3: =A3*Parametros!B4*Parametros!B3 -> 240
A4: =Volumes!A4 -> 5000 | B4: =A4*Parametros!B2 -> 15250 | C4: =A4*Parametros!B4*Parametros!B3 -> 600
A5: =Volumes!A5 -> 20000 | B5: =A5*Parametros!B2 -> 61000 | C5: =A5*Parametros!B4*Parametros!B3 -> 2400

Sheet Pricing
A1: Entidades | B1: Setup Sugerido | C1: Mensalidade Sugerida
A2: =Volumes!A2 -> 150 | B2: =Custos!B2/(1-Parametros!B5) -> 1525 | C2: =Custos!C2/(1-Parametros!B5) -> 60
A3: =Volumes!A3 -> 2000 | B3: =Custos!B3/(1-Parametros!B5) -> 20333.333 | C3: =Custos!C3/(1-Parametros!B5) -> 800
A4: =Volumes!A4 -> 5000 | B4: =Custos!B4/(1-Parametros!B5) -> 50833.333 | C4: =Custos!C4/(1-Parametros!B5) -> 2000
A5: =Volumes!A5 -> 20000 | B5: =Custos!B5/(1-Parametros!B5) -> 203333.33 | C5: =Custos!C5/(1-Parametros!B5) -> 8000

Sheet Financial_Model
A1: Entidades | B1: Setup | C1: Mensalidade | D1: CAC (Exemplo) | E1: LTV (24 meses) | F1: Receita Total 24m | G1: Custo Total 24m | H1: Lucro Bruto 24m | I1: Payback (meses) | J1: Break Even Receita Mensal
A2: =Pricing!A2 -> 150 | B2: =Pricing!B2 -> 1525 | C2: =Pricing!C2 -> 60 | D2: =Dashboard_Cliente!$C$12 -> 2000 | E2: =C2*Parametros!$B$6 -> 1440 | F2: =B2+E2 -> 2965 | G2: =Custos!B2+(Custos!C2*Parametros!$B$6) -> 889.5 | H2: =F2-G2 -> 2075.5 | I2: =D2/C2 -> 33.333333 | J2: =G2/Parametros!$B$6 -> 37.0625
A3: =Pricing!A3 -> 2000 | B3: =Pricing!B3 -> 20333.333 | C3: =Pricing!C3 -> 800 | D3: =Dashboard_Cliente!$C$12 -> 2000 | E3: =C3*Parametros!$B$6 -> 19200 | F3: =B3+E3 -> 39533.333 | G3: =Custos!B3+(Custos!C3*Parametros!$B$6) -> 11860 | H3: =F3-G3 -> 27673.333 | I3: =D3/C3 -> 2.5 | J3: =G3/Parametros!$B$6 -> 494.16667
A4: =Pricing!A4 -> 5000 | B4: =Pricing!B4 -> 50833.333 | C4: =Pricing!C4 -> 2000 | D4: =Dashboard_Cliente!$C$12 -> 2000 | E4: =C4*Parametros!$B$6 -> 48000 | F4: =B4+E4 -> 98833.333 | G4: =Custos!B4+(Custos!C4*Parametros!$B$6) -> 29650 | H4: =F4-G4 -> 69183.333 | I4: =D4/C4 -> 1 | J4: =G4/Parametros!$B$6 -> 1235.4167
A5: =Pricing!A5 -> 20000 | B5: =Pricing!B5 -> 203333.33 | C5: =Pricing!C5 -> 8000 | D5: =Dashboard_Cliente!$C$12 -> 2000 | E5: =C5*Parametros!$B$6 -> 192000 | F5: =B5+E5 -> 395333.33 | G5: =Custos!B5+(Custos!C5*Parametros!$B$6) -> 118600 | H5: =F5-G5 -> 276733.33 | I5: =D5/C5 -> 0.25 | J5: =G5/Parametros!$B$6 -> 4941.6667
